iflow_mcp_tripadvisor_mcp-0.1.0.dist-info/licenses/LICENSE
tripadvisor_mcp/__init__.py
tripadvisor_mcp/main.py
tripadvisor_mcp/server.py
iflow_mcp_tripadvisor_mcp-0.1.0.dist-info/METADATA
iflow_mcp_tripadvisor_mcp-0.1.0.dist-info/WHEEL
iflow_mcp_tripadvisor_mcp-0.1.0.dist-info/entry_points.txt
iflow_mcp_tripadvisor_mcp-0.1.0.dist-info/top_level.txt
iflow_mcp_tripadvisor_mcp-0.1.0.dist-info/RECORD
